pyxdf/__init__.py
pyxdf/__version__.py
pyxdf/pyxdf.pxd
pyxdf/pyxdf.py
pyxdf/cli/__init__.py
pyxdf/cli/playback_lsl.py
pyxdf/cli/print_metadata.py
pyxdf-1.17.1.dist-info/METADATA
pyxdf-1.17.1.dist-info/WHEEL
pyxdf-1.17.1.dist-info/licenses/LICENSE
pyxdf-1.17.1.dist-info/RECORD
