Metadata-Version: 2.4
Name: pyxdf
Version: 1.17.1
Summary: Python library for importing XDF (Extensible Data Format)
Project-URL: Repository, https://github.com/xdf-modules/pyxdf
Project-URL: Issues, https://github.com/xdf-modules/pyxdf/issues
Project-URL: Changelog, https://github.com/xdf-modules/pyxdf/blob/main/CHANGELOG.md
Author-email: Christian Kothe <christian.kothe@intheon.io>, Chadwick Boulay <chadwick.boulay@gmail.com>, Clemens Brunner <clemens.brunner@gmail.com>
License-Expression: BSD-3-Clause
License-File: LICENSE
Keywords: LSL,Lab Streaming Layer,XDF,biosignals,file format,pyxdf,stream
Classifier: Development Status :: 4 - Beta
Classifier: Intended Audience :: Developers
Classifier: Intended Audience :: Science/Research
Classifier: Operating System :: MacOS
Classifier: Operating System :: Microsoft :: Windows
Classifier: Operating System :: POSIX :: Linux
Classifier: Programming Language :: Python :: 3
Classifier: Programming Language :: Python :: 3.9
Classifier: Programming Language :: Python :: 3.10
Classifier: Programming Language :: Python :: 3.11
Classifier: Programming Language :: Python :: 3.12
Classifier: Programming Language :: Python :: 3.13
Classifier: Topic :: Scientific/Engineering
Requires-Python: >=3.9
Requires-Dist: numpy>=2.0.2
Provides-Extra: playback
Requires-Dist: pylsl>=1.17.6; extra == 'playback'
